django_likertblock-0.4.0.dist-info/DESCRIPTION.rst
django_likertblock-0.4.0.dist-info/METADATA
django_likertblock-0.4.0.dist-info/RECORD
django_likertblock-0.4.0.dist-info/WHEEL
django_likertblock-0.4.0.dist-info/metadata.json
django_likertblock-0.4.0.dist-info/top_level.txt
likertblock/__init__.py
likertblock/__init__.pyc
likertblock/models.py
likertblock/models.pyc
likertblock/urls.py
likertblock/urls.pyc
likertblock/views.py
likertblock/views.pyc
likertblock/migrations/0001_initial.py
likertblock/migrations/0001_initial.pyc
likertblock/migrations/__init__.py
likertblock/migrations/__init__.pyc
likertblock/templates/likertblock/edit_question.html
likertblock/templates/likertblock/likertblock.html
likertblock/templates/likertblock/question.html
likertblock/templates/likertblock/question_confirm_delete.html
likertblock/templates/likertblock/questionnaire_detail.html
likertblock/templatetags/__init__.py
likertblock/templatetags/__init__.pyc
likertblock/templatetags/likertgetresponse.py
likertblock/templatetags/likertgetresponse.pyc
likertblock/tests/__init__.py
likertblock/tests/__init__.pyc
likertblock/tests/test_models.py
likertblock/tests/test_models.pyc
likertblock/tests/test_views.py
likertblock/tests/test_views.pyc
