Metadata-Version: 2.0
Name: django-likertblock
Version: 0.4.0
Summary: Basic Likert PageBlock
Home-page: UNKNOWN
Author: Anders Pearson
Author-email: anders@columbia.edu
License: BSD
Platform: any
Requires-Dist: Markdown
Requires-Dist: django-markwhat
Requires-Dist: django-pagetree
